{
  "recordId": "161643598",
  "url": "https://www.luogu.com.cn/record/161643598?_contentOnly=1",
  "status": 200,
  "contentType": "application/json",
  "fetchedAt": "2026-06-23T04:06:55.599Z",
  "rawText": "{\"code\":200,\"currentTemplate\":\"RecordShow\",\"currentData\":{\"record\":{\"detail\":{\"compileResult\":{\"success\":false,\"message\":\"\\/tmp\\/compiler_mu5piitd\\/src: \\u5728\\u51fd\\u6570\\u2018int main()\\u2019\\u4e2d:\\n\\/tmp\\/compiler_mu5piitd\\/src:5:10: \\u9519\\u8bef\\uff1a\\u2018n\\u2019 was not declared in this scope; did you mean \\u2018yn\\u2019?\\n    5 |     cin>>n;\\n      |          ^\\n      |          yn\\n\\/tmp\\/compiler_mu5piitd\\/src:9:8: \\u9519\\u8bef\\uff1a\\u2018a\\u2019\\u5728\\u6b64\\u4f5c\\u7528\\u57df\\u4e2d\\u5c1a\\u672a\\u58f0\\u660e\\n    9 |   cin>>a[i]>>b[i]>>t[i];\\n      |        ^\\n\\/tmp\\/compiler_mu5piitd\\/src:9:14: \\u9519\\u8bef\\uff1a\\u2018b\\u2019\\u5728\\u6b64\\u4f5c\\u7528\\u57df\\u4e2d\\u5c1a\\u672a\\u58f0\\u660e\\n    9 |   cin>>a[i]>>b[i]>>t[i];\\n      |              ^\\n\\/tmp\\/compiler_mu5piitd\\/src:9:20: \\u9519\\u8bef\\uff1a\\u2018t\\u2019\\u5728\\u6b64\\u4f5c\\u7528\\u57df\\u4e2d\\u5c1a\\u672a\\u58f0\\u660e\\n    9 |   cin>>a[i]>>b[i]>>t[i];\\n      |                    ^\\n\\/tmp\\/compiler_mu5piitd\\/src:13:12: \\u9519\\u8bef\\uff1a\\u2018a\\u2019\\u5728\\u6b64\\u4f5c\\u7528\\u57df\\u4e2d\\u5c1a\\u672a\\u58f0\\u660e\\n   13 |         if(a[i]==0)\\n      |            ^\\n\\/tmp\\/compiler_mu5piitd\\/src:15:9: \\u9519\\u8bef\\uff1a\\u2018b\\u2019\\u5728\\u6b64\\u4f5c\\u7528\\u57df\\u4e2d\\u5c1a\\u672a\\u58f0\\u660e\\n   15 |    map+=b[i];\\n      |         ^\\n\\/tmp\\/compiler_mu5piitd\\/src:22:32: \\u9519\\u8bef\\uff1a\\u2018t\\u2019\\u5728\\u6b64\\u4f5c\\u7528\\u57df\\u4e2d\\u5c1a\\u672a\\u58f0\\u660e\\n   22 |                 if (a[j]==0 && t[i]-t[j]<=45 && b[j]>=b[i])\\n      |                                ^\\n\\/tmp\\/compiler_mu5piitd\\/src:22:49: \\u9519\\u8bef\\uff1a\\u2018b\\u2019\\u5728\\u6b64\\u4f5c\\u7528\\u57df\\u4e2d\\u5c1a\\u672a\\u58f0\\u660e\\n   22 |                 if (a[j]==0 && t[i]-t[j]<=45 && b[j]>=b[i])\\n      |                                                 ^\\n\\/tmp\\/compiler_mu5piitd\\/src:31:10: \\u9519\\u8bef\\uff1a\\u2018b\\u2019\\u5728\\u6b64\\u4f5c\\u7528\\u57df\\u4e2d\\u5c1a\\u672a\\u58f0\\u660e\\n   31 |     map+=b[i];\\n      |          ^\\n\",\"opt2\":false,\"__CLASS_NAME\":\"Luogu\\\\DataClass\\\\Record\\\\JudgeResult\\\\CompileResult\"},\"judgeResult\":{\"subtasks\":[],\"finishedCaseCount\":0,\"status\":0,\"time\":0,\"memory\":0,\"score\":0,\"__CLASS_NAME\":\"Luogu\\\\DataClass\\\\Record\\\\JudgeResult\\\\JudgeResult\"},\"version\":400,\"__CLASS_NAME\":\"Luogu\\\\DataClass\\\\Record\\\\RecordDetail\"},\"sourceCode\":\"#include <bits\\/stdc++.h>\\r\\nusing namespace std;       \\r\\nint main()\\r\\n{\\r\\n    cin>>n;\\r\\n    int n,a[n],b[n],t[n],map=0;     \\r\\n    for (int i=1;i<=n;i++)\\r\\n\\t{\\r\\n\\t\\tcin>>a[i]>>b[i]>>t[i];\\r\\n\\t}\\r\\n    for (int i=1;i<=n;i++)\\r\\n\\t{\\r\\n        if(a[i]==0)\\r\\n\\t\\t{\\r\\n\\t\\t\\tmap+=b[i];\\r\\n\\t\\t}\\r\\n        else\\r\\n\\t\\t{\\r\\n            bool f=false;\\r\\n            for (int j=max(1,i-45);j<i;j++)\\r\\n\\t\\t\\t{\\r\\n                if (a[j]==0 && t[i]-t[j]<=45 && b[j]>=b[i])\\r\\n\\t\\t\\t\\t{\\r\\n                    a[j]=1;\\r\\n                    f=true;\\r\\n                    break;\\r\\n                }\\r\\n            }\\r\\n            if(!f)\\r\\n\\t\\t\\t{\\r\\n\\t\\t\\t\\tmap+=b[i];\\r\\n\\t\\t\\t}\\r\\n        }\\r\\n    }\\r\\n    cout<<map<<endl;\\r\\n    return 0;\\r\\n}\",\"time\":0,\"memory\":0,\"problem\":{\"pid\":\"P5661\",\"title\":\"[CSP-J 2019] \\u516c\\u4ea4\\u6362\\u4e58\",\"difficulty\":2,\"fullScore\":100,\"type\":\"P\"},\"contest\":null,\"sourceCodeLength\":650,\"submitTime\":1717844434,\"language\":28,\"user\":{\"uid\":1024038,\"name\":\"lin_yna\",\"avatar\":\"https:\\/\\/cdn.luogu.com.cn\\/upload\\/usericon\\/1024038.png\",\"slogan\":\"rp++\",\"badge\":null,\"isAdmin\":false,\"isBanned\":false,\"color\":\"Green\",\"ccfLevel\":5,\"xcpcLevel\":0,\"background\":\"\"},\"id\":161643598,\"status\":2,\"enableO2\":true,\"score\":null},\"testCaseGroup\":[[0,1,2,3,4,5,6,7,8,9,10,11,12,13,14,15,16,17,18,19]],\"showStatus\":true},\"currentTitle\":\"R161643598\",\"currentTheme\":{\"id\":321387,\"header\":{\"imagePath\":\"https:\\/\\/i.loli.net\\/2019\\/05\\/02\\/5cca6b2808d2a.jpg\",\"color\":[[94,114,228,1],[130,94,228,1]],\"blur\":0,\"brightness\":0,\"degree\":87,\"repeat\":0,\"position\":[100,1],\"size\":[-1,-1],\"type\":1,\"__CLASS_NAME\":\"Luogu\\\\DataClass\\\\User\\\\ThemeConfig\\\\HeaderFooterConfig\"},\"sideNav\":{\"logoBackgroundColor\":[94,114,228,1],\"color\":[94,114,228,1],\"invertColor\":true,\"__CLASS_NAME\":\"Luogu\\\\DataClass\\\\User\\\\ThemeConfig\\\\SideNavConfig\"},\"footer\":{\"imagePath\":\"https:\\/\\/i.loli.net\\/2019\\/05\\/02\\/5cca6b2808d2a.jpg\",\"color\":[[119,149,248,1],[103,114,229,1],[85,90,191,1]],\"blur\":0,\"brightness\":0,\"degree\":150,\"repeat\":0,\"position\":[1,100],\"size\":[0,0],\"type\":1,\"__CLASS_NAME\":\"Luogu\\\\DataClass\\\\User\\\\ThemeConfig\\\\HeaderFooterConfig\"}},\"currentTime\":1782187615,\"currentUser\":{\"followingCount\":99,\"followerCount\":41,\"ranking\":11089,\"eloValue\":1304,\"blogAddress\":\"https:\\/\\/www.luogu.com.cn\\/blog\\/asos1324\\/\",\"unreadMessageCount\":0,\"unreadNoticeCount\":0,\"uid\":1024038,\"name\":\"lin_yna\",\"avatar\":\"https:\\/\\/cdn.luogu.com.cn\\/upload\\/usericon\\/1024038.png\",\"slogan\":\"rp++\",\"badge\":null,\"isAdmin\":false,\"isBanned\":false,\"color\":\"Green\",\"ccfLevel\":5,\"xcpcLevel\":0,\"background\":\"\",\"verified\":true}}",
  "json": {
    "code": 200,
    "currentTemplate": "RecordShow",
    "currentData": {
      "record": {
        "detail": {
          "compileResult": {
            "success": false,
            "message": "/tmp/compiler_mu5piitd/src: 在函数‘int main()’中:\n/tmp/compiler_mu5piitd/src:5:10: 错误：‘n’ was not declared in this scope; did you mean ‘yn’?\n    5 |     cin>>n;\n      |          ^\n      |          yn\n/tmp/compiler_mu5piitd/src:9:8: 错误：‘a’在此作用域中尚未声明\n    9 |   cin>>a[i]>>b[i]>>t[i];\n      |        ^\n/tmp/compiler_mu5piitd/src:9:14: 错误：‘b’在此作用域中尚未声明\n    9 |   cin>>a[i]>>b[i]>>t[i];\n      |              ^\n/tmp/compiler_mu5piitd/src:9:20: 错误：‘t’在此作用域中尚未声明\n    9 |   cin>>a[i]>>b[i]>>t[i];\n      |                    ^\n/tmp/compiler_mu5piitd/src:13:12: 错误：‘a’在此作用域中尚未声明\n   13 |         if(a[i]==0)\n      |            ^\n/tmp/compiler_mu5piitd/src:15:9: 错误：‘b’在此作用域中尚未声明\n   15 |    map+=b[i];\n      |         ^\n/tmp/compiler_mu5piitd/src:22:32: 错误：‘t’在此作用域中尚未声明\n   22 |                 if (a[j]==0 && t[i]-t[j]<=45 && b[j]>=b[i])\n      |                                ^\n/tmp/compiler_mu5piitd/src:22:49: 错误：‘b’在此作用域中尚未声明\n   22 |                 if (a[j]==0 && t[i]-t[j]<=45 && b[j]>=b[i])\n      |                                                 ^\n/tmp/compiler_mu5piitd/src:31:10: 错误：‘b’在此作用域中尚未声明\n   31 |     map+=b[i];\n      |          ^\n",
            "opt2": false,
            "__CLASS_NAME": "Luogu\\DataClass\\Record\\JudgeResult\\CompileResult"
          },
          "judgeResult": {
            "subtasks": [],
            "finishedCaseCount": 0,
            "status": 0,
            "time": 0,
            "memory": 0,
            "score": 0,
            "__CLASS_NAME": "Luogu\\DataClass\\Record\\JudgeResult\\JudgeResult"
          },
          "version": 400,
          "__CLASS_NAME": "Luogu\\DataClass\\Record\\RecordDetail"
        },
        "sourceCode": "#include <bits/stdc++.h>\r\nusing namespace std;       \r\nint main()\r\n{\r\n    cin>>n;\r\n    int n,a[n],b[n],t[n],map=0;     \r\n    for (int i=1;i<=n;i++)\r\n\t{\r\n\t\tcin>>a[i]>>b[i]>>t[i];\r\n\t}\r\n    for (int i=1;i<=n;i++)\r\n\t{\r\n        if(a[i]==0)\r\n\t\t{\r\n\t\t\tmap+=b[i];\r\n\t\t}\r\n        else\r\n\t\t{\r\n            bool f=false;\r\n            for (int j=max(1,i-45);j<i;j++)\r\n\t\t\t{\r\n                if (a[j]==0 && t[i]-t[j]<=45 && b[j]>=b[i])\r\n\t\t\t\t{\r\n                    a[j]=1;\r\n                    f=true;\r\n                    break;\r\n                }\r\n            }\r\n            if(!f)\r\n\t\t\t{\r\n\t\t\t\tmap+=b[i];\r\n\t\t\t}\r\n        }\r\n    }\r\n    cout<<map<<endl;\r\n    return 0;\r\n}",
        "time": 0,
        "memory": 0,
        "problem": {
          "pid": "P5661",
          "title": "[CSP-J 2019] 公交换乘",
          "difficulty": 2,
          "fullScore": 100,
          "type": "P"
        },
        "contest": null,
        "sourceCodeLength": 650,
        "submitTime": 1717844434,
        "language": 28,
        "user": {
          "uid": 1024038,
          "name": "lin_yna",
          "avatar": "https://cdn.luogu.com.cn/upload/usericon/1024038.png",
          "slogan": "rp++",
          "badge": null,
          "isAdmin": false,
          "isBanned": false,
          "color": "Green",
          "ccfLevel": 5,
          "xcpcLevel": 0,
          "background": ""
        },
        "id": 161643598,
        "status": 2,
        "enableO2": true,
        "score": null
      },
      "testCaseGroup": [
        [
          0,
          1,
          2,
          3,
          4,
          5,
          6,
          7,
          8,
          9,
          10,
          11,
          12,
          13,
          14,
          15,
          16,
          17,
          18,
          19
        ]
      ],
      "showStatus": true
    },
    "currentTitle": "R161643598",
    "currentTheme": {
      "id": 321387,
      "header": {
        "imagePath": "https://i.loli.net/2019/05/02/5cca6b2808d2a.jpg",
        "color": [
          [
            94,
            114,
            228,
            1
          ],
          [
            130,
            94,
            228,
            1
          ]
        ],
        "blur": 0,
        "brightness": 0,
        "degree": 87,
        "repeat": 0,
        "position": [
          100,
          1
        ],
        "size": [
          -1,
          -1
        ],
        "type": 1,
        "__CLASS_NAME": "Luogu\\DataClass\\User\\ThemeConfig\\HeaderFooterConfig"
      },
      "sideNav": {
        "logoBackgroundColor": [
          94,
          114,
          228,
          1
        ],
        "color": [
          94,
          114,
          228,
          1
        ],
        "invertColor": true,
        "__CLASS_NAME": "Luogu\\DataClass\\User\\ThemeConfig\\SideNavConfig"
      },
      "footer": {
        "imagePath": "https://i.loli.net/2019/05/02/5cca6b2808d2a.jpg",
        "color": [
          [
            119,
            149,
            248,
            1
          ],
          [
            103,
            114,
            229,
            1
          ],
          [
            85,
            90,
            191,
            1
          ]
        ],
        "blur": 0,
        "brightness": 0,
        "degree": 150,
        "repeat": 0,
        "position": [
          1,
          100
        ],
        "size": [
          0,
          0
        ],
        "type": 1,
        "__CLASS_NAME": "Luogu\\DataClass\\User\\ThemeConfig\\HeaderFooterConfig"
      }
    },
    "currentTime": 1782187615,
    "currentUser": {
      "followingCount": 99,
      "followerCount": 41,
      "ranking": 11089,
      "eloValue": 1304,
      "blogAddress": "https://www.luogu.com.cn/blog/asos1324/",
      "unreadMessageCount": 0,
      "unreadNoticeCount": 0,
      "uid": 1024038,
      "name": "lin_yna",
      "avatar": "https://cdn.luogu.com.cn/upload/usericon/1024038.png",
      "slogan": "rp++",
      "badge": null,
      "isAdmin": false,
      "isBanned": false,
      "color": "Green",
      "ccfLevel": 5,
      "xcpcLevel": 0,
      "background": "",
      "verified": true
    }
  }
}